[
    {
        "epoch": 1,
        "lr": 0.001,
        "train_loss": 1.6367436930524586,
        "train_acc": 49.97879560889583,
        "val_loss": 1.3600273132324219,
        "val_acc": 55.534351145038165,
        "val_macro_f1": 0.19197170302426997,
        "val_auroc": NaN
    },
    {
        "epoch": 2,
        "lr": 0.001,
        "train_loss": 1.147465344199293,
        "train_acc": 62.76505506999216,
        "val_loss": 1.2500152160193174,
        "val_acc": 58.587786259541986,
        "val_macro_f1": 0.21804103203675038,
        "val_auroc": NaN
    },
    {
        "epoch": 3,
        "lr": 0.001,
        "train_loss": 1.0070390318085118,
        "train_acc": 67.34520775792556,
        "val_loss": 1.1587022169855714,
        "val_acc": 60.49618320610687,
        "val_macro_f1": 0.2608385724348926,
        "val_auroc": NaN
    },
    {
        "epoch": 4,
        "lr": 0.001,
        "train_loss": 0.9074008429930107,
        "train_acc": 70.22900763358778,
        "val_loss": 1.110899258205909,
        "val_acc": 61.641221374045806,
        "val_macro_f1": 0.2735275400293136,
        "val_auroc": NaN
    },
    {
        "epoch": 5,
        "lr": 0.001,
        "train_loss": 0.8168476947896859,
        "train_acc": 73.26123833757421,
        "val_loss": 1.0872242860211672,
        "val_acc": 62.97709923664122,
        "val_macro_f1": 0.2918126758511493,
        "val_auroc": NaN
    },
    {
        "epoch": 6,
        "lr": 0.001,
        "train_loss": 0.7387787573311266,
        "train_acc": 75.42408821681883,
        "val_loss": 1.0776669405798875,
        "val_acc": 63.93129770992366,
        "val_macro_f1": 0.2988977997772135,
        "val_auroc": NaN
    },
    {
        "epoch": 7,
        "lr": 0.001,
        "train_loss": 0.6582619361295045,
        "train_acc": 78.32909245770092,
        "val_loss": 1.0732634690881686,
        "val_acc": 64.8854961832061,
        "val_macro_f1": 0.345776098914471,
        "val_auroc": NaN
    },
    {
        "epoch": 8,
        "lr": 0.001,
        "train_loss": 0.5809235927207274,
        "train_acc": 81.40373202154856,
        "val_loss": 1.0626176345439358,
        "val_acc": 63.358778625954194,
        "val_macro_f1": 0.3367279393091621,
        "val_auroc": NaN
    },
    {
        "epoch": 9,
        "lr": 0.001,
        "train_loss": 0.5120678382773234,
        "train_acc": 84.07548772732619,
        "val_loss": 1.086060174548899,
        "val_acc": 64.69465648854961,
        "val_macro_f1": 0.35180808590933793,
        "val_auroc": NaN
    },
    {
        "epoch": 10,
        "lr": 0.001,
        "train_loss": 0.4468411054269453,
        "train_acc": 86.87446978619991,
        "val_loss": 1.0489903374482656,
        "val_acc": 64.50381679389314,
        "val_macro_f1": 0.35750585949638275,
        "val_auroc": NaN
    },
    {
        "epoch": 11,
        "lr": 0.001,
        "train_loss": 0.39263657905774363,
        "train_acc": 89.46140790167655,
        "val_loss": 1.1068426589019427,
        "val_acc": 63.93129770992366,
        "val_macro_f1": 0.34016742134284733,
        "val_auroc": NaN
    },
    {
        "epoch": 12,
        "lr": 0.001,
        "train_loss": 0.3243177925205716,
        "train_acc": 91.963528316844,
        "val_loss": 1.082967636694435,
        "val_acc": 65.64885496183206,
        "val_macro_f1": 0.3667150300194547,
        "val_auroc": NaN
    },
    {
        "epoch": 13,
        "lr": 0.001,
        "train_loss": 0.27961858730380873,
        "train_acc": 94.12637818314647,
        "val_loss": 1.1192701135882894,
        "val_acc": 64.8854961832061,
        "val_macro_f1": 0.3789720691658894,
        "val_auroc": NaN
    },
    {
        "epoch": 14,
        "lr": 0.001,
        "train_loss": 0.23758734841029253,
        "train_acc": 95.6955046455571,
        "val_loss": 1.1452287854129122,
        "val_acc": 65.2671755725191,
        "val_macro_f1": 0.3848118449672476,
        "val_auroc": NaN
    },
    {
        "epoch": 15,
        "lr": 0.001,
        "train_loss": 0.20299115552044805,
        "train_acc": 96.35284136512504,
        "val_loss": 1.1537319635616914,
        "val_acc": 66.41221374045801,
        "val_macro_f1": 0.42705634085684147,
        "val_auroc": NaN
    }
]