[
    {
        "epoch": 5,
        "lr": 0.0009938503261272714,
        "train_loss": 1.0586188354535107,
        "train_acc": 60.76339695769376,
        "val_loss": 0.8814144183934661,
        "val_acc": 67.87564766839378,
        "val_balanced_acc": 0.21298701298701297,
        "val_macro_recall": 0.21298701298701297,
        "val_macro_f1": 0.2077956480605487,
        "val_macro_precision": 0.27911678637935616,
        "val_auc_macro_ovr": 0.8172944990178117,
        "val_mean_auc_all_diagnoses": 0.8172944990178117,
        "val_mean_ap_all_diagnoses": 0.3663758175907499,
        "val_mean_sensitivity": 0.21298701298701297,
        "val_mean_specificity": 0.8809167112537899,
        "val_mean_ppv": 0.27911678637935616,
        "val_mean_npv": 0.9534987285326626,
        "val_melanoma_auc80": 0.7508305647840532,
        "val_malignant_vs_benign_auc": 0.8360280658938377,
        "roc_curve_path": "experiments\\20260416_145617_resnet50_scratch_diffaug_lr0.001_bs128_seed42\\roc_curves\\epoch_005_roc.png",
        "confusion_matrix_path": "experiments\\20260416_145617_resnet50_scratch_diffaug_lr0.001_bs128_seed42\\confusion_matrices\\epoch_005_confusion_matrix.png",
        "val_predictions_path": "experiments\\20260416_145617_resnet50_scratch_diffaug_lr0.001_bs128_seed42\\predictions\\val_predictions_epoch_05.csv",
        "detailed_metrics_path": "experiments\\20260416_145617_resnet50_scratch_diffaug_lr0.001_bs128_seed42\\metrics\\epoch_005_detailed_metrics.json"
    },
    {
        "epoch": 10,
        "lr": 0.0009755527298894294,
        "train_loss": 0.9101535811187009,
        "train_acc": 64.96374700434835,
        "val_loss": 0.7176217575765027,
        "val_acc": 67.87564766839378,
        "val_balanced_acc": 0.2784288881849858,
        "val_macro_recall": 0.2784288881849858,
        "val_macro_f1": 0.26517297875558815,
        "val_macro_precision": 0.25513177587693653,
        "val_auc_macro_ovr": 0.9236373259437979,
        "val_mean_auc_all_diagnoses": 0.9236373259437979,
        "val_mean_ap_all_diagnoses": 0.47939853961797774,
        "val_mean_sensitivity": 0.2784288881849858,
        "val_mean_specificity": 0.9139049089036417,
        "val_mean_ppv": 0.25513177587693653,
        "val_mean_npv": 0.931142480583027,
        "val_melanoma_auc80": 0.8682170542635659,
        "val_malignant_vs_benign_auc": 0.9136668700427089,
        "roc_curve_path": "experiments\\20260416_145617_resnet50_scratch_diffaug_lr0.001_bs128_seed42\\roc_curves\\epoch_010_roc.png",
        "confusion_matrix_path": "experiments\\20260416_145617_resnet50_scratch_diffaug_lr0.001_bs128_seed42\\confusion_matrices\\epoch_010_confusion_matrix.png",
        "val_predictions_path": "experiments\\20260416_145617_resnet50_scratch_diffaug_lr0.001_bs128_seed42\\predictions\\val_predictions_epoch_10.csv",
        "detailed_metrics_path": "experiments\\20260416_145617_resnet50_scratch_diffaug_lr0.001_bs128_seed42\\metrics\\epoch_010_detailed_metrics.json"
    },
    {
        "epoch": 15,
        "lr": 0.00094555775883209,
        "train_loss": 0.8473022573043311,
        "train_acc": 67.30560883570436,
        "val_loss": 0.6226518799603912,
        "val_acc": 76.16580310880829,
        "val_balanced_acc": 0.43030152193915266,
        "val_macro_recall": 0.43030152193915266,
        "val_macro_f1": 0.44089980489803576,
        "val_macro_precision": 0.5181799999797978,
        "val_auc_macro_ovr": 0.9488076000157611,
        "val_mean_auc_all_diagnoses": 0.9488076000157611,
        "val_mean_ap_all_diagnoses": 0.5883772932495954,
        "val_mean_sensitivity": 0.43030152193915266,
        "val_mean_specificity": 0.9441488901611967,
        "val_mean_ppv": 0.5181799999797978,
        "val_mean_npv": 0.9503320836981975,
        "val_melanoma_auc80": 0.877076411960133,
        "val_malignant_vs_benign_auc": 0.9215985356924954,
        "roc_curve_path": "experiments\\20260416_145617_resnet50_scratch_diffaug_lr0.001_bs128_seed42\\roc_curves\\epoch_015_roc.png",
        "confusion_matrix_path": "experiments\\20260416_145617_resnet50_scratch_diffaug_lr0.001_bs128_seed42\\confusion_matrices\\epoch_015_confusion_matrix.png",
        "val_predictions_path": "experiments\\20260416_145617_resnet50_scratch_diffaug_lr0.001_bs128_seed42\\predictions\\val_predictions_epoch_15.csv",
        "detailed_metrics_path": "experiments\\20260416_145617_resnet50_scratch_diffaug_lr0.001_bs128_seed42\\metrics\\epoch_015_detailed_metrics.json"
    },
    {
        "epoch": 20,
        "lr": 0.0009046039886902867,
        "train_loss": 0.7881744982143354,
        "train_acc": 69.30577551944026,
        "val_loss": 0.6281402271646293,
        "val_acc": 73.57512953367875,
        "val_balanced_acc": 0.3855947478769779,
        "val_macro_recall": 0.3855947478769779,
        "val_macro_f1": 0.42369878856534043,
        "val_macro_precision": 0.5852087990245884,
        "val_auc_macro_ovr": 0.9477837029534582,
        "val_mean_auc_all_diagnoses": 0.9477837029534582,
        "val_mean_ap_all_diagnoses": 0.5562093667289928,
        "val_mean_sensitivity": 0.3855947478769779,
        "val_mean_specificity": 0.9203801878128143,
        "val_mean_ppv": 0.5852087990245884,
        "val_mean_npv": 0.9457313523179655,
        "val_melanoma_auc80": 0.8884274640088593,
        "val_malignant_vs_benign_auc": 0.9305979255643684,
        "roc_curve_path": "experiments\\20260416_145617_resnet50_scratch_diffaug_lr0.001_bs128_seed42\\roc_curves\\epoch_020_roc.png",
        "confusion_matrix_path": "experiments\\20260416_145617_resnet50_scratch_diffaug_lr0.001_bs128_seed42\\confusion_matrices\\epoch_020_confusion_matrix.png",
        "val_predictions_path": "experiments\\20260416_145617_resnet50_scratch_diffaug_lr0.001_bs128_seed42\\predictions\\val_predictions_epoch_20.csv",
        "detailed_metrics_path": "experiments\\20260416_145617_resnet50_scratch_diffaug_lr0.001_bs128_seed42\\metrics\\epoch_020_detailed_metrics.json"
    },
    {
        "epoch": 25,
        "lr": 0.0008536998372026809,
        "train_loss": 0.7234106120769953,
        "train_acc": 72.18934910606768,
        "val_loss": 0.6307403578041749,
        "val_acc": 75.12953367875647,
        "val_balanced_acc": 0.4112539028915336,
        "val_macro_recall": 0.4112539028915336,
        "val_macro_f1": 0.4316340341969198,
        "val_macro_precision": 0.4658730158730159,
        "val_auc_macro_ovr": 0.9419364911813083,
        "val_mean_auc_all_diagnoses": 0.9419364911813083,
        "val_mean_ap_all_diagnoses": 0.5859923772571067,
        "val_mean_sensitivity": 0.4112539028915336,
        "val_mean_specificity": 0.9348535897756808,
        "val_mean_ppv": 0.4658730158730159,
        "val_mean_npv": 0.9464399663970543,
        "val_melanoma_auc80": 0.8906423034330011,
        "val_malignant_vs_benign_auc": 0.9409701037217816,
        "roc_curve_path": "experiments\\20260416_145617_resnet50_scratch_diffaug_lr0.001_bs128_seed42\\roc_curves\\epoch_025_roc.png",
        "confusion_matrix_path": "experiments\\20260416_145617_resnet50_scratch_diffaug_lr0.001_bs128_seed42\\confusion_matrices\\epoch_025_confusion_matrix.png",
        "val_predictions_path": "experiments\\20260416_145617_resnet50_scratch_diffaug_lr0.001_bs128_seed42\\predictions\\val_predictions_epoch_25.csv",
        "detailed_metrics_path": "experiments\\20260416_145617_resnet50_scratch_diffaug_lr0.001_bs128_seed42\\metrics\\epoch_025_detailed_metrics.json"
    },
    {
        "epoch": 30,
        "lr": 0.0007940987335200908,
        "train_loss": 0.652949909283048,
        "train_acc": 74.78956580986647,
        "val_loss": 0.5992421350330887,
        "val_acc": 77.720207253886,
        "val_balanced_acc": 0.4665007466401195,
        "val_macro_recall": 0.4665007466401195,
        "val_macro_f1": 0.5085466539913001,
        "val_macro_precision": 0.6398017441495701,
        "val_auc_macro_ovr": 0.9407145411911652,
        "val_mean_auc_all_diagnoses": 0.9407145411911652,
        "val_mean_ap_all_diagnoses": 0.5397233394571961,
        "val_mean_sensitivity": 0.4665007466401195,
        "val_mean_specificity": 0.9393352084594108,
        "val_mean_ppv": 0.6398017441495701,
        "val_mean_npv": 0.9550230182027404,
        "val_melanoma_auc80": 0.886766334440753,
        "val_malignant_vs_benign_auc": 0.9350213544844417,
        "roc_curve_path": "experiments\\20260416_145617_resnet50_scratch_diffaug_lr0.001_bs128_seed42\\roc_curves\\epoch_030_roc.png",
        "confusion_matrix_path": "experiments\\20260416_145617_resnet50_scratch_diffaug_lr0.001_bs128_seed42\\confusion_matrices\\epoch_030_confusion_matrix.png",
        "val_predictions_path": "experiments\\20260416_145617_resnet50_scratch_diffaug_lr0.001_bs128_seed42\\predictions\\val_predictions_epoch_30.csv",
        "detailed_metrics_path": "experiments\\20260416_145617_resnet50_scratch_diffaug_lr0.001_bs128_seed42\\metrics\\epoch_030_detailed_metrics.json"
    },
    {
        "epoch": 35,
        "lr": 0.0007272682546199041,
        "train_loss": 0.5805792148405934,
        "train_acc": 77.79814988079146,
        "val_loss": 0.6084602150892346,
        "val_acc": 76.16580310880829,
        "val_balanced_acc": 0.5107399279002066,
        "val_macro_recall": 0.5107399279002066,
        "val_macro_f1": 0.5012143453872777,
        "val_macro_precision": 0.49792556557506723,
        "val_auc_macro_ovr": 0.9249170355548181,
        "val_mean_auc_all_diagnoses": 0.9249170355548181,
        "val_mean_ap_all_diagnoses": 0.5631167818182446,
        "val_mean_sensitivity": 0.5107399279002066,
        "val_mean_specificity": 0.9417372062673256,
        "val_mean_ppv": 0.49792556557506723,
        "val_mean_npv": 0.9472974809017336,
        "val_melanoma_auc80": 0.8524363233665558,
        "val_malignant_vs_benign_auc": 0.9263270286760219,
        "roc_curve_path": "experiments\\20260416_145617_resnet50_scratch_diffaug_lr0.001_bs128_seed42\\roc_curves\\epoch_035_roc.png",
        "confusion_matrix_path": "experiments\\20260416_145617_resnet50_scratch_diffaug_lr0.001_bs128_seed42\\confusion_matrices\\epoch_035_confusion_matrix.png",
        "val_predictions_path": "experiments\\20260416_145617_resnet50_scratch_diffaug_lr0.001_bs128_seed42\\predictions\\val_predictions_epoch_35.csv",
        "detailed_metrics_path": "experiments\\20260416_145617_resnet50_scratch_diffaug_lr0.001_bs128_seed42\\metrics\\epoch_035_detailed_metrics.json"
    },
    {
        "epoch": 40,
        "lr": 0.0006548539886902866,
        "train_loss": 0.4980334020205384,
        "train_acc": 81.08175681306776,
        "val_loss": 0.6478796144223584,
        "val_acc": 77.720207253886,
        "val_balanced_acc": 0.45493800624462644,
        "val_macro_recall": 0.45493800624462644,
        "val_macro_f1": 0.4879132452395013,
        "val_macro_precision": 0.617566926050996,
        "val_auc_macro_ovr": 0.9331619009151904,
        "val_mean_auc_all_diagnoses": 0.9331619009151904,
        "val_mean_ap_all_diagnoses": 0.5324989124781173,
        "val_mean_sensitivity": 0.45493800624462644,
        "val_mean_specificity": 0.9391830992982093,
        "val_mean_ppv": 0.617566926050996,
        "val_mean_npv": 0.9567643844283369,
        "val_melanoma_auc80": 0.8120155038759691,
        "val_malignant_vs_benign_auc": 0.9133618059792556,
        "roc_curve_path": "experiments\\20260416_145617_resnet50_scratch_diffaug_lr0.001_bs128_seed42\\roc_curves\\epoch_040_roc.png",
        "confusion_matrix_path": "experiments\\20260416_145617_resnet50_scratch_diffaug_lr0.001_bs128_seed42\\confusion_matrices\\epoch_040_confusion_matrix.png",
        "val_predictions_path": "experiments\\20260416_145617_resnet50_scratch_diffaug_lr0.001_bs128_seed42\\predictions\\val_predictions_epoch_40.csv",
        "detailed_metrics_path": "experiments\\20260416_145617_resnet50_scratch_diffaug_lr0.001_bs128_seed42\\metrics\\epoch_040_detailed_metrics.json"
    },
    {
        "epoch": 45,
        "lr": 0.0005786390152875957,
        "train_loss": 0.4277685857289075,
        "train_acc": 83.97366446568098,
        "val_loss": 0.6856756074440912,
        "val_acc": 77.720207253886,
        "val_balanced_acc": 0.4806145074437757,
        "val_macro_recall": 0.4806145074437757,
        "val_macro_f1": 0.49679083449847566,
        "val_macro_precision": 0.5446845404828599,
        "val_auc_macro_ovr": 0.9422457815843356,
        "val_mean_auc_all_diagnoses": 0.9422457815843356,
        "val_mean_ap_all_diagnoses": 0.5786626406898078,
        "val_mean_sensitivity": 0.4806145074437757,
        "val_mean_specificity": 0.9404793792531494,
        "val_mean_ppv": 0.5446845404828599,
        "val_mean_npv": 0.9538598509383026,
        "val_melanoma_auc80": 0.8668327796234774,
        "val_malignant_vs_benign_auc": 0.9226662599145821,
        "roc_curve_path": "experiments\\20260416_145617_resnet50_scratch_diffaug_lr0.001_bs128_seed42\\roc_curves\\epoch_045_roc.png",
        "confusion_matrix_path": "experiments\\20260416_145617_resnet50_scratch_diffaug_lr0.001_bs128_seed42\\confusion_matrices\\epoch_045_confusion_matrix.png",
        "val_predictions_path": "experiments\\20260416_145617_resnet50_scratch_diffaug_lr0.001_bs128_seed42\\predictions\\val_predictions_epoch_45.csv",
        "detailed_metrics_path": "experiments\\20260416_145617_resnet50_scratch_diffaug_lr0.001_bs128_seed42\\metrics\\epoch_045_detailed_metrics.json"
    },
    {
        "epoch": 50,
        "lr": 0.0005005000000000003,
        "train_loss": 0.32518205444299536,
        "train_acc": 88.24068674614792,
        "val_loss": 0.6364881593946348,
        "val_acc": 80.31088082901555,
        "val_balanced_acc": 0.5142378237325973,
        "val_macro_recall": 0.5142378237325973,
        "val_macro_f1": 0.5175745654231024,
        "val_macro_precision": 0.5343846629560915,
        "val_auc_macro_ovr": 0.9448495203791083,
        "val_mean_auc_all_diagnoses": 0.9448495203791083,
        "val_mean_ap_all_diagnoses": 0.5789091637468223,
        "val_mean_sensitivity": 0.5142378237325973,
        "val_mean_specificity": 0.9545682645643095,
        "val_mean_ppv": 0.5343846629560915,
        "val_mean_npv": 0.9575059945973988,
        "val_melanoma_auc80": 0.812015503875969,
        "val_malignant_vs_benign_auc": 0.9383770591824283,
        "roc_curve_path": "experiments\\20260416_145617_resnet50_scratch_diffaug_lr0.001_bs128_seed42\\roc_curves\\epoch_050_roc.png",
        "confusion_matrix_path": "experiments\\20260416_145617_resnet50_scratch_diffaug_lr0.001_bs128_seed42\\confusion_matrices\\epoch_050_confusion_matrix.png",
        "val_predictions_path": "experiments\\20260416_145617_resnet50_scratch_diffaug_lr0.001_bs128_seed42\\predictions\\val_predictions_epoch_50.csv",
        "detailed_metrics_path": "experiments\\20260416_145617_resnet50_scratch_diffaug_lr0.001_bs128_seed42\\metrics\\epoch_050_detailed_metrics.json"
    },
    {
        "epoch": 55,
        "lr": 0.00042236098471240487,
        "train_loss": 0.25562260555310967,
        "train_acc": 91.18259854987916,
        "val_loss": 0.6204424312077655,
        "val_acc": 78.23834196891191,
        "val_balanced_acc": 0.49056556103594434,
        "val_macro_recall": 0.49056556103594434,
        "val_macro_f1": 0.5057605449227236,
        "val_macro_precision": 0.5290455045481198,
        "val_auc_macro_ovr": 0.9493487433122901,
        "val_mean_auc_all_diagnoses": 0.9493487433122901,
        "val_mean_ap_all_diagnoses": 0.5942417914329722,
        "val_mean_sensitivity": 0.49056556103594434,
        "val_mean_specificity": 0.9498001437796973,
        "val_mean_ppv": 0.5290455045481198,
        "val_mean_npv": 0.952737806625085,
        "val_melanoma_auc80": 0.8981173864894795,
        "val_malignant_vs_benign_auc": 0.9447834045149481,
        "roc_curve_path": "experiments\\20260416_145617_resnet50_scratch_diffaug_lr0.001_bs128_seed42\\roc_curves\\epoch_055_roc.png",
        "confusion_matrix_path": "experiments\\20260416_145617_resnet50_scratch_diffaug_lr0.001_bs128_seed42\\confusion_matrices\\epoch_055_confusion_matrix.png",
        "val_predictions_path": "experiments\\20260416_145617_resnet50_scratch_diffaug_lr0.001_bs128_seed42\\predictions\\val_predictions_epoch_55.csv",
        "detailed_metrics_path": "experiments\\20260416_145617_resnet50_scratch_diffaug_lr0.001_bs128_seed42\\metrics\\epoch_055_detailed_metrics.json"
    },
    {
        "epoch": 60,
        "lr": 0.00034614601130971405,
        "train_loss": 0.20116814417470066,
        "train_acc": 92.94107843591866,
        "val_loss": 0.7449358673911021,
        "val_acc": 74.61139896373057,
        "val_balanced_acc": 0.4634089777818001,
        "val_macro_recall": 0.4634089777818001,
        "val_macro_f1": 0.4626039963023537,
        "val_macro_precision": 0.4628587500574,
        "val_auc_macro_ovr": 0.9297688250266989,
        "val_mean_auc_all_diagnoses": 0.9297688250266989,
        "val_mean_ap_all_diagnoses": 0.5220257446071146,
        "val_mean_sensitivity": 0.4634089777818001,
        "val_mean_specificity": 0.9444154879653556,
        "val_mean_ppv": 0.4628587500574,
        "val_mean_npv": 0.9434890971043313,
        "val_melanoma_auc80": 0.8939645625692136,
        "val_malignant_vs_benign_auc": 0.9412751677852349,
        "roc_curve_path": "experiments\\20260416_145617_resnet50_scratch_diffaug_lr0.001_bs128_seed42\\roc_curves\\epoch_060_roc.png",
        "confusion_matrix_path": "experiments\\20260416_145617_resnet50_scratch_diffaug_lr0.001_bs128_seed42\\confusion_matrices\\epoch_060_confusion_matrix.png",
        "val_predictions_path": "experiments\\20260416_145617_resnet50_scratch_diffaug_lr0.001_bs128_seed42\\predictions\\val_predictions_epoch_60.csv",
        "detailed_metrics_path": "experiments\\20260416_145617_resnet50_scratch_diffaug_lr0.001_bs128_seed42\\metrics\\epoch_060_detailed_metrics.json"
    },
    {
        "epoch": 65,
        "lr": 0.0002737317453800965,
        "train_loss": 0.1706603755987389,
        "train_acc": 94.21618471702782,
        "val_loss": 0.9248278598093616,
        "val_acc": 74.61139896373057,
        "val_balanced_acc": 0.4298414709564536,
        "val_macro_recall": 0.4298414709564536,
        "val_macro_f1": 0.44869829882869583,
        "val_macro_precision": 0.48663157570720594,
        "val_auc_macro_ovr": 0.9353302546104433,
        "val_mean_auc_all_diagnoses": 0.9353302546104433,
        "val_mean_ap_all_diagnoses": 0.5723248056998129,
        "val_mean_sensitivity": 0.4298414709564536,
        "val_mean_specificity": 0.9359148379453074,
        "val_mean_ppv": 0.48663157570720594,
        "val_mean_npv": 0.9491432380686696,
        "val_melanoma_auc80": 0.8253045404208195,
        "val_malignant_vs_benign_auc": 0.924039048200122,
        "roc_curve_path": "experiments\\20260416_145617_resnet50_scratch_diffaug_lr0.001_bs128_seed42\\roc_curves\\epoch_065_roc.png",
        "confusion_matrix_path": "experiments\\20260416_145617_resnet50_scratch_diffaug_lr0.001_bs128_seed42\\confusion_matrices\\epoch_065_confusion_matrix.png",
        "val_predictions_path": "experiments\\20260416_145617_resnet50_scratch_diffaug_lr0.001_bs128_seed42\\predictions\\val_predictions_epoch_65.csv",
        "detailed_metrics_path": "experiments\\20260416_145617_resnet50_scratch_diffaug_lr0.001_bs128_seed42\\metrics\\epoch_065_detailed_metrics.json"
    },
    {
        "epoch": 70,
        "lr": 0.00020690126647990978,
        "train_loss": 0.13637939651356765,
        "train_acc": 95.70797567099707,
        "val_loss": 1.0096443205917438,
        "val_acc": 75.64766839378238,
        "val_balanced_acc": 0.4516101784394468,
        "val_macro_recall": 0.4516101784394468,
        "val_macro_f1": 0.49270832775806356,
        "val_macro_precision": 0.5999330094009727,
        "val_auc_macro_ovr": 0.9279765576341765,
        "val_mean_auc_all_diagnoses": 0.9279765576341765,
        "val_mean_ap_all_diagnoses": 0.5449988123026037,
        "val_mean_sensitivity": 0.4516101784394468,
        "val_mean_specificity": 0.9347093811494827,
        "val_mean_ppv": 0.5999330094009727,
        "val_mean_npv": 0.9499936837290737,
        "val_melanoma_auc80": 0.7178848283499446,
        "val_malignant_vs_benign_auc": 0.9177852348993288,
        "roc_curve_path": "experiments\\20260416_145617_resnet50_scratch_diffaug_lr0.001_bs128_seed42\\roc_curves\\epoch_070_roc.png",
        "confusion_matrix_path": "experiments\\20260416_145617_resnet50_scratch_diffaug_lr0.001_bs128_seed42\\confusion_matrices\\epoch_070_confusion_matrix.png",
        "val_predictions_path": "experiments\\20260416_145617_resnet50_scratch_diffaug_lr0.001_bs128_seed42\\predictions\\val_predictions_epoch_70.csv",
        "detailed_metrics_path": "experiments\\20260416_145617_resnet50_scratch_diffaug_lr0.001_bs128_seed42\\metrics\\epoch_070_detailed_metrics.json"
    },
    {
        "epoch": 75,
        "lr": 0.0001473001627973196,
        "train_loss": 0.1113812048312614,
        "train_acc": 96.69139098739592,
        "val_loss": 0.9295794617944431,
        "val_acc": 76.68393782383419,
        "val_balanced_acc": 0.47054768692399357,
        "val_macro_recall": 0.47054768692399357,
        "val_macro_f1": 0.49167399517946714,
        "val_macro_precision": 0.529584483365996,
        "val_auc_macro_ovr": 0.9289024216704933,
        "val_mean_auc_all_diagnoses": 0.9289024216704933,
        "val_mean_ap_all_diagnoses": 0.5352203684454536,
        "val_mean_sensitivity": 0.47054768692399357,
        "val_mean_specificity": 0.9388792565079511,
        "val_mean_ppv": 0.529584483365996,
        "val_mean_npv": 0.9507843017510573,
        "val_melanoma_auc80": 0.8629568106312292,
        "val_malignant_vs_benign_auc": 0.9238865161683955,
        "roc_curve_path": "experiments\\20260416_145617_resnet50_scratch_diffaug_lr0.001_bs128_seed42\\roc_curves\\epoch_075_roc.png",
        "confusion_matrix_path": "experiments\\20260416_145617_resnet50_scratch_diffaug_lr0.001_bs128_seed42\\confusion_matrices\\epoch_075_confusion_matrix.png",
        "val_predictions_path": "experiments\\20260416_145617_resnet50_scratch_diffaug_lr0.001_bs128_seed42\\predictions\\val_predictions_epoch_75.csv",
        "detailed_metrics_path": "experiments\\20260416_145617_resnet50_scratch_diffaug_lr0.001_bs128_seed42\\metrics\\epoch_075_detailed_metrics.json"
    },
    {
        "epoch": 80,
        "lr": 9.639601130971386e-05,
        "train_loss": 0.09280783841089166,
        "train_acc": 97.43311946794822,
        "val_loss": 0.8822132398427459,
        "val_acc": 79.27461139896373,
        "val_balanced_acc": 0.4594680000603346,
        "val_macro_recall": 0.4594680000603346,
        "val_macro_f1": 0.4961131412024269,
        "val_macro_precision": 0.5882883855296505,
        "val_auc_macro_ovr": 0.9369112490402277,
        "val_mean_auc_all_diagnoses": 0.9369112490402277,
        "val_mean_ap_all_diagnoses": 0.5720594413005403,
        "val_mean_sensitivity": 0.4594680000603346,
        "val_mean_specificity": 0.9492152415721666,
        "val_mean_ppv": 0.5882883855296505,
        "val_mean_npv": 0.9601526798047286,
        "val_melanoma_auc80": 0.8510520487264672,
        "val_malignant_vs_benign_auc": 0.9341061622940817,
        "roc_curve_path": "experiments\\20260416_145617_resnet50_scratch_diffaug_lr0.001_bs128_seed42\\roc_curves\\epoch_080_roc.png",
        "confusion_matrix_path": "experiments\\20260416_145617_resnet50_scratch_diffaug_lr0.001_bs128_seed42\\confusion_matrices\\epoch_080_confusion_matrix.png",
        "val_predictions_path": "experiments\\20260416_145617_resnet50_scratch_diffaug_lr0.001_bs128_seed42\\predictions\\val_predictions_epoch_80.csv",
        "detailed_metrics_path": "experiments\\20260416_145617_resnet50_scratch_diffaug_lr0.001_bs128_seed42\\metrics\\epoch_080_detailed_metrics.json"
    },
    {
        "epoch": 85,
        "lr": 5.5442241167910324e-05,
        "train_loss": 0.08841053723012302,
        "train_acc": 97.57479789982499,
        "val_loss": 0.9289969323212619,
        "val_acc": 78.23834196891191,
        "val_balanced_acc": 0.4705823792931807,
        "val_macro_recall": 0.4705823792931807,
        "val_macro_f1": 0.4932456985613132,
        "val_macro_precision": 0.5379120879120879,
        "val_auc_macro_ovr": 0.937516140731442,
        "val_mean_auc_all_diagnoses": 0.937516140731442,
        "val_mean_ap_all_diagnoses": 0.5709273687129326,
        "val_mean_sensitivity": 0.4705823792931807,
        "val_mean_specificity": 0.9439434065188683,
        "val_mean_ppv": 0.5379120879120879,
        "val_mean_npv": 0.9565382969340106,
        "val_melanoma_auc80": 0.8167220376522701,
        "val_malignant_vs_benign_auc": 0.9292251372788286,
        "roc_curve_path": "experiments\\20260416_145617_resnet50_scratch_diffaug_lr0.001_bs128_seed42\\roc_curves\\epoch_085_roc.png",
        "confusion_matrix_path": "experiments\\20260416_145617_resnet50_scratch_diffaug_lr0.001_bs128_seed42\\confusion_matrices\\epoch_085_confusion_matrix.png",
        "val_predictions_path": "experiments\\20260416_145617_resnet50_scratch_diffaug_lr0.001_bs128_seed42\\predictions\\val_predictions_epoch_85.csv",
        "detailed_metrics_path": "experiments\\20260416_145617_resnet50_scratch_diffaug_lr0.001_bs128_seed42\\metrics\\epoch_085_detailed_metrics.json"
    }
]